Metadata-Version: 2.1
Name: scTail
Version: 0.1.8
Summary: scTail: Detection alternative PAS in single cells
Home-page: https://github.com/StatBiomed/scTail
Author: ['Ruiyan Hou']
Author-email: ruiyan@connect.hku.hk
License: Apache-2.0
Keywords: Polyadenylation sites,single-cell RNA-seq
Requires-Python: >=3.9
Provides-Extra: docs
License-File: LICENSE
